prettypyplot/__init__.py
prettypyplot/colors.py
prettypyplot/pyplot.py
prettypyplot/style.py
prettypyplot/subplots.py
prettypyplot/texts.py
prettypyplot/tools.py
prettypyplot/_cmaps/__init__.py
prettypyplot/_cmaps/bownair.py
prettypyplot/_cmaps/discrete.py
prettypyplot/_cmaps/gdv_discrete.py
prettypyplot/_cmaps/macaw.py
prettypyplot/_cmaps/paula2.py
prettypyplot/_cmaps/tol_discrete.py
prettypyplot/_cmaps/turbo.py
prettypyplot/stylelib/default.mplstyle
prettypyplot/stylelib/latex.mplstyle
prettypyplot/stylelib/minimal.mplstyle
prettypyplot-0.12.0.dist-info/METADATA
prettypyplot-0.12.0.dist-info/WHEEL
prettypyplot-0.12.0.dist-info/RECORD
