Metadata-Version: 2.4
Name: prettypyplot
Version: 0.12.0
Summary: Wrapper for matplotlib to generate pretty plots.
Project-URL: Documentation, https://braniii.github.io/prettypyplot
Project-URL: Repository, https://github.com/braniii/prettypyplot
Project-URL: Issues, https://github.com/braniii/prettypyplot/issues
Project-URL: Changelog, https://braniii.github.io/prettypyplot/changelog
Author: braniii
License-Expression: MIT
Keywords: matplotlib,pyplot
Classifier: License :: OSI Approved :: BSD License
Classifier: Programming Language :: Python :: 3
Classifier: Programming Language :: Python :: 3.9
Classifier: Programming Language :: Python :: 3.10
Classifier: Programming Language :: Python :: 3.11
Classifier: Programming Language :: Python :: 3.12
Classifier: Programming Language :: Python :: 3.13
Requires-Python: >=3.9
Requires-Dist: decorit>=0.2.0
Requires-Dist: matplotlib
Requires-Dist: numpy
